README.rst
setup.cfg
setup.py
cssocialuser/__init__.py
cssocialuser/admin.py
cssocialuser/forms.py
cssocialuser/models.py
cssocialuser/urls.py
cssocialuser/views.py
cssocialuser.egg-info/PKG-INFO
cssocialuser.egg-info/SOURCES.txt
cssocialuser.egg-info/dependency_links.txt
cssocialuser.egg-info/entry_points.txt
cssocialuser.egg-info/not-zip-safe
cssocialuser.egg-info/requires.txt
cssocialuser.egg-info/top_level.txt
cssocialuser/utils/__init__.py
cssocialuser/utils/load_images.py
cssocialuser/utils/slug.py