Metadata-Version: 1.1
Name: cssocialuser
Version: 0.43
Summary: CsSocialUser
Home-page: https://github.com/codesyntax/cssocialuser
Author: Jatsu Argarate
Author-email: jargarate@codesyntax.com
License: New BSD
Platform: UNKNOWN
Requires: django(>=1.5)
